README.rst
setup.py
fc_tools/Matplotlib.py
fc_tools/Mayavi.py
fc_tools/Sys.py
fc_tools/__init__.py
fc_tools/colors.py
fc_tools/git.py
fc_tools/graphics.py
fc_tools/math.py
fc_tools/others.py
fc_tools.egg-info/PKG-INFO
fc_tools.egg-info/SOURCES.txt
fc_tools.egg-info/dependency_links.txt
fc_tools.egg-info/requires.txt
fc_tools.egg-info/top_level.txt