Metadata-Version: 1.1
Name: fc_tools
Version: 0.0.21
Summary: Some functions used in fc_hypermesh, fc_bench, fc_simesh, ... packages
Home-page: http://www.math.univ-paris13.fr/~cuvelier/software
Author: Francois Cuvelier
Author-email: cuvelier@math.univ-paris13.fr
License: BSD
Platform: UNKNOWN
Classifier: Topic :: Scientific/Engineering :: Mathematics
